qa_check/__init__.py
qa_check/qa_checking.py
retrieve_data/__init__.py
retrieve_data/cntdb.py
upload_result/__init__.py
upload_result/upld_file.py
cpnnaming-0.0.2.dist-info/METADATA
cpnnaming-0.0.2.dist-info/WHEEL
cpnnaming-0.0.2.dist-info/top_level.txt
cpnnaming-0.0.2.dist-info/RECORD
