Metadata-Version: 2.1
Name: cpnnaming
Version: 0.0.2
Summary: Developed by Brado, this is a package to perform QA on campaign names
Home-page: https://github.com/pypa/sampleproject
Author: Jenny Wang
Author-email: wangzh0510@hotmail.com
License: UNKNOWN
Platform: UNKNOWN
Classifier: Programming Language :: Python :: 3
Classifier: License :: OSI Approved :: MIT License
Classifier: Operating System :: OS Independent
